citypay/__init__.py
citypay/api_client.py
citypay/api_response.py
citypay/configuration.py
citypay/exceptions.py
citypay/model_utils.py
citypay/py.typed
citypay/rest.py
citypay/api/__init__.py
citypay/api/authorisation_and_payment_api.py
citypay/api/batch_processing_api.py
citypay/api/card_holder_account_api.py
citypay/api/direct_post_api.py
citypay/api/operational_functions_api.py
citypay/api/paylink_api.py
citypay/api/payment_intent_api.py
citypay/api/reporting_api.py
citypay/api/web_hooks.py
citypay/apis/__init__.py
citypay/models/__init__.py
citypay/models/account_create.py
citypay/models/account_status.py
citypay/models/acknowledgement.py
citypay/models/acl_check_request.py
citypay/models/acl_check_response_model.py
citypay/models/adjustment_condition.py
citypay/models/adjustments.py
citypay/models/airline_advice.py
citypay/models/airline_segment.py
citypay/models/api_key.py
citypay/models/auth_reference.py
citypay/models/auth_references.py
citypay/models/auth_request.py
citypay/models/auth_response.py
citypay/models/authen_required.py
citypay/models/batch.py
citypay/models/batch_report_request.py
citypay/models/batch_report_response_model.py
citypay/models/batch_transaction.py
citypay/models/batch_transaction_report_request.py
citypay/models/batch_transaction_report_response.py
citypay/models/batch_transaction_result_model.py
citypay/models/bin.py
citypay/models/bin_lookup.py
citypay/models/c_res_auth_request.py
citypay/models/capture_request.py
citypay/models/card.py
citypay/models/card_holder_account.py
citypay/models/card_status.py
citypay/models/card_tokenisation_request.py
citypay/models/card_tokenisation_response.py
citypay/models/charge_request.py
citypay/models/check_batch_status.py
citypay/models/check_batch_status_response.py
citypay/models/contact_details.py
citypay/models/decision.py
citypay/models/direct_post_request.py
citypay/models/direct_token_auth_request.py
citypay/models/domain_key_check_request.py
citypay/models/domain_key_request.py
citypay_api_client-1.1.7.dist-info/METADATA
citypay_api_client-1.1.7.dist-info/WHEEL
citypay_api_client-1.1.7.dist-info/top_level.txt
citypay_api_client-1.1.7.dist-info/RECORD
