Metadata-Version: 2.4
Name: citypay_api_client
Version: 1.1.7
Summary: CityPay Payment API
Home-page: 
Author: CityPay Support
Author-email: support@citypay.com
Keywords: OpenAPI,OpenAPI-Generator,CityPay Payment API
Requires-Dist: urllib3<3.0.0,>=2.1.0
Requires-Dist: python-dateutil>=2.8.2
Requires-Dist: pydantic>=2
Requires-Dist: typing-extensions>=4.7.1
Dynamic: author
Dynamic: author-email
Dynamic: description
Dynamic: description-content-type
Dynamic: keywords
Dynamic: requires-dist
Dynamic: summary
